chip/ChipUtility.py
chip/clusters/CHIPClusters.py
chip/clusters/ClusterObjects.py
chip/clusters/Objects.py
chip/clusters/TestObjects.py
chip/clusters/Types.py
chip/clusters/enum.py
chip/tlv/__init__.py
chip/tlv/tlvlist.py
myssix_chip_clusters-0.3.0.dist-info/LICENSE
myssix_chip_clusters-0.3.0.dist-info/METADATA
myssix_chip_clusters-0.3.0.dist-info/WHEEL
myssix_chip_clusters-0.3.0.dist-info/top_level.txt
myssix_chip_clusters-0.3.0.dist-info/RECORD
